Metadata-Version: 2.1
Name: app-app
Version: 0.1.0
Summary: A Python package for JWT-based authentication
Home-page: https://github.com/raviforcebolt/jwt_authenticator.git
Author: Mohd Ravi
Author-email: mohd.ravi@cloudanalogy.com
License: UNKNOWN
Platform: UNKNOWN
Classifier: Programming Language :: Python :: 3
Classifier: License :: OSI Approved :: MIT License
Classifier: Operating System :: OS Independent
Requires-Python: >=3.8
